README.md
setup.cfg
setup.py
src/dktoparserhtml/__init__.py
src/dktoparserhtml/_html_to_markdown.py
src/dktoparserhtml/_html_to_utf8.py
src/dktoparserhtml/_recurs_function.py
src/dktoparserhtml/_remove_duplicates.py
src/dktoparserhtml/_simplify_html.py
src/dktoparserhtml/_utf8_to_html.py
src/dktoparserhtml.egg-info/PKG-INFO
src/dktoparserhtml.egg-info/SOURCES.txt
src/dktoparserhtml.egg-info/dependency_links.txt
src/dktoparserhtml.egg-info/requires.txt
src/dktoparserhtml.egg-info/top_level.txt