Metadata-Version: 2.1
Name: dktoparserhtml
Version: 1.0.1
Summary: Parser UTF8/HTML <-> pure HTML -> UTF8/Markdown
Home-page: https://discord-catho.frama.io/parserhtml/
Author: Pierre
License: UNKNOWN
Project-URL: Source Code, https://framagit.org/discord-catho/parserhtml
Keywords: parser,html,utf8,markdown
Platform: UNKNOWN
Requires-Python: <4,>=3.9
Provides-Extra: doc
Provides-Extra: tests
